tsapython/__init__.py
tsapython/core.py
tsapython/py.typed
tsapython-2.0.0.dist-info/licenses/LICENSE
tsapython-2.0.0.dist-info/WHEEL
tsapython-2.0.0.dist-info/METADATA
tsapython-2.0.0.dist-info/RECORD
