Metadata-Version: 2.4
Name: tsapython
Version: 2.0.0
Summary: An UNOFFICIAL Python API for the tinySA series of devices
Author: LC-Linkous
Author-email: LC-Linkous <L.C.Linkous@gmail.com>
License-Expression: GPL-2.0-only
License-File: LICENSE
Classifier: Programming Language :: Python :: 3
Classifier: Operating System :: OS Independent
Requires-Dist: matplotlib>=3.10.5
Requires-Dist: numpy>=2.2.6
Requires-Dist: pandas>=2.3.1
Requires-Dist: pyserial>=3.5
Requires-Python: >=3.10
Project-URL: Issues, https://github.com/LC-Linkous/tinySA_python/issues
Project-URL: Repository, https://github.com/LC-Linkous/tinySA_python
